{
  "decision": "buy a new phone",
  "risk_tolerance": 3,
  "num_prompts": 3,
  "temperature": 0.7,
  "pros": [
    {
      "description": "New Oppo phone with modern features",
      "impact": 8,
      "likelihood": 1.0,
      "cost": 1000.0
    }
  ],
  "cons": [
    {
      "description": "High cost investment",
      "impact": 7,
      "likelihood": 1.0,
      "cost": 1000.0
    }
  ],
  "opportunity_costs": [
    {
      "description": "Could save money for other investments",
      "impact": 6,
      "likelihood": 0.8,
      "value": 1000.0,
      "input_source": "HUMAN"
    }
  ],
  "timestamp": "2025-01-04T16:45:00.000Z",
  "ai_analysis": {
    "analysis": {
      "summary": "**Summary of Key Points**\n\nThe decision to buy a new phone involves weighing the pros and cons, considering opportunity costs, risk assessment, potential short-term and long-term consequences, and a c...",
      "confidence": 0.8,
      "recommendations": [
        "**Summary of Key Points**\n\nThe decision to buy a new phone involves weighing the pros and cons, considering opportunity costs, risk assessment, potential short-term and long-term consequences, and a clear recommendation based on these factors.\n\n**Quantitative Analysis**\n\nTo calculate the weighted impact of each factor:\n\n1. New Oppo phone with modern features:\n\t* Impact: 8/10\n\t* Likelihood: 1.0 (very likely)\n\t* Weighted Impact: 8 x 1.0 = 8\n2. High cost investment:\n\t* Impact: 7/10\n\t* Likelihood: 1.0 (very likely)\n\t* Weighted Impact: 7 x 1.0 = 7\n3. Opportunity Costs:\n\t* Impact: 6/10\n\t* Likelihood: 0.8 (moderately likely)\n\t* Value: $1000.0\n\t* Weighted Impact: 6 x 0.8 = 4.8\n\n**Cost-Benefit Analysis**\n\nTo assess the financial implications:\n\n1. New Oppo phone:\n\t* Cost: $1000.0\n2. Opportunity Costs:\n\t* Value: -$1000.0 (opportunity cost)\n\nNet Benefit/Cost: ($1000.0) - $1000.0 = -$1000.0\n\n**Risk Assessment**\n\nBased on the likelihood and impact scores, with a user's risk tolerance of 3/10:\n\n1. New Oppo phone:\n\t* Likelihood: 1.0 (very likely)\n\t* Impact: 8 (high)\n\t* Risk Score: 8 x 1.0 = 8\n2. High cost investment:\n\t* Likelihood: 1.0 (very likely)\n\t* Impact: 7 (moderate-high)\n\t* Risk Score: 7 x 1.0 = 7\n\nTotal Risk Score: 8 + 7 = 15\n\n**Opportunity Costs Evaluation**\n\nThe opportunity costs of $1000.0 could be used for other investments or savings, which may have a lower risk profile and potentially higher returns.\n\n**Potential Short-term and Long-term Consequences**\n\nBuying the new Oppo phone may provide modern features and convenience in the short term. However, it comes with a significant upfront cost ($1000.0) that may impact financial flexibility and savings.\n\nIn the long term, not investing $1000.0 in the opportunity costs could result in missed investment opportunities or lower returns on alternative investments.\n\n**Final Recommendation**\n\nBased on the quantitative analysis and risk tolerance (3/10), it is recommended to:\n\n* Consider delaying the purchase of the new Oppo phone until a more financially stable period.\n* Allocate the $1000.0 towards other investments or savings, potentially with a lower risk profile and higher returns.\n* Monitor financial flexibility and adjust spending habits accordingly.\n\nThis decision prioritizes long-term financial stability over short-term convenience, taking into account the user's moderate risk tolerance."
      ]
    },
    "evaluation": {
      "pros_analysis": {
        "total_impact": 8.0,
        "total_cost": 1000.0
      },
      "cons_analysis": {
        "total_impact": 7.0,
        "total_cost": 1000.0
      },
      "risk_assessment": {
        "raw_risk_score": 7.0,
        "risk_tolerance": 3,
        "adjusted_risk_score": 5.6
      },
      "opportunity_costs_analysis": {
        "total_impact": 4.800000000000001,
        "total_value": 1000.0
      }
    },
    "metadata": {
      "model_used": "llama3.2",
      "timestamp": "2025-01-04T17:11:37.386945",
      "processing_time": 31.416625
    }
  }
}